jl95/pytools/ppjava.py
jl95/pytools/swjava.py
jl95terceira/pytools/ppjava.py
jl95terceira/pytools/swjava.py
jl95terceira_pytools_java-0.1.2.dist-info/METADATA
jl95terceira_pytools_java-0.1.2.dist-info/WHEEL
jl95terceira_pytools_java-0.1.2.dist-info/entry_points.txt
jl95terceira_pytools_java-0.1.2.dist-info/RECORD
