Metadata-Version: 2.4
Name: jl95terceira_pytools_java
Version: 0.1.2
Summary: Python command line tools collection (general) - Java
Project-URL: Homepage, https://github.com/jl95terceira/project-pytools-java
Project-URL: Issues, https://github.com/jl95terceira/project-pytools-java/issues
Author-email: Joao Luis Ornelas da Silva <jl95terceira@gmail.com>
Classifier: License :: OSI Approved :: MIT License
Classifier: Operating System :: OS Independent
Classifier: Programming Language :: Python :: 3
Requires-Python: >=3.12
Requires-Dist: jl95terceira-pytools-pp>=0.3.1
Requires-Dist: jl95terceira-pytools>=0.15.1
